pipeline_sdk_test24/__init__.py
pipeline_sdk_test24/auth_service.py
pipeline_sdk_test24/inference_pipeline.py
pipeline_sdk_test24/model_inference_dsl_component.py
pipeline_sdk_test24/model_train_dsl_component.py
pipeline_sdk_test24/model_validate_dsl_component.py
pipeline_sdk_test24/pipeline_util.py
pipeline_sdk_test24/run_inference_pipeline.py
pipeline_sdk_test24/run_training_pipeline.py
pipeline_sdk_test24/run_validate_pipeline.py
pipeline_sdk_test24/train_pipeline.py
pipeline_sdk_test24/validate_pipeline.py
pipeline_sdk_test24-2.0.0.dist-info/METADATA
pipeline_sdk_test24-2.0.0.dist-info/WHEEL
pipeline_sdk_test24-2.0.0.dist-info/top_level.txt
pipeline_sdk_test24-2.0.0.dist-info/RECORD
