Metadata-Version: 2.4
Name: pipeline_sdk_test24
Version: 2.0.0
Summary: Multiple files in sigle sdk for pipeline execution.
Author: Saurav Kumar
Author-email: Saurav.Kumar@cognizant.com
Classifier: Programming Language :: Python :: 3
Classifier: License :: OSI Approved :: MIT License
Classifier: Operating System :: OS Independent
Requires-Python: >=3.6
Dynamic: author
Dynamic: author-email
Dynamic: classifier
Dynamic: requires-python
Dynamic: summary
